{
  "bookKey": "NCE2",
  "title": "25.Do the English Speak English",
  "filename": "25.Do the English Speak English",
  "lines": [
    {
      "time": 2.8,
      "english": "Do they speak English?",
      "chinese": "他们说英语吗？",
      "raw": "Do they speak English? | 他们说英语吗？"
    },
    {
      "time": 11.76,
      "english": "Why does the writer not understand the porter?",
      "chinese": "为什么作者听不懂搬运工的话？",
      "raw": "Why does the writer not understand the porter? | 为什么作者听不懂搬运工的话？"
    },
    {
      "time": 17.21,
      "english": "I arrived in London at last.",
      "chinese": "我终于抵达伦敦了。",
      "raw": "I arrived in London at last. | 我终于抵达伦敦了。"
    },
    {
      "time": 20.55,
      "english": "The railway station was big, black and dark.",
      "chinese": "火车站又大，又黑，又暗。",
      "raw": "The railway station was big, black and dark. | 火车站又大，又黑，又暗。"
    },
    {
      "time": 25.85,
      "english": "I did not know the way to my hotel, so I asked a porter.",
      "chinese": "我不知道去旅馆的路，所以我问了一位搬运工。",
      "raw": "I did not know the way to my hotel, so I asked a porter. | 我不知道去旅馆的路，所以我问了一位搬运工。"
    },
    {
      "time": 32.1,
      "english": "I not only spoke English very carefully, but very clearly as well.",
      "chinese": "我不仅非常仔细地说英语，而且说得非常清楚。",
      "raw": "I not only spoke English very carefully, but very clearly as well. | 我不仅非常仔细地说英语，而且说得非常清楚。"
    },
    {
      "time": 39.66,
      "english": "The porter, however, could not understand me.",
      "chinese": "然而，那个搬运工却听不懂我。",
      "raw": "The porter, however, could not understand me. | 然而，那个搬运工却听不懂我。"
    },
    {
      "time": 43.94,
      "english": "I repeated my question several times and at last he understood.",
      "chinese": "我重复了我的问题好几次，最后他终于明白了。",
      "raw": "I repeated my question several times and at last he understood. | 我重复了我的问题好几次，最后他终于明白了。"
    },
    {
      "time": 50.87,
      "english": "he answered me, but he spoke neither slowly nor clearly.",
      "chinese": "他回答了我，但他既说得不慢也不清楚。",
      "raw": "he answered me, but he spoke neither slowly nor clearly. | 他回答了我，但他既说得不慢也不清楚。"
    },
    {
      "time": 56.92,
      "english": "'I am a foreigner,' I said.",
      "chinese": "“我是一个外国人，”我说。",
      "raw": "'I am a foreigner,' I said. | “我是一个外国人，”我说。"
    },
    {
      "time": 60.62,
      "english": "Then he spoke slowly, but I could not understand him.",
      "chinese": "然后他慢慢地说，但我仍然听不懂他。",
      "raw": "Then he spoke slowly, but I could not understand him. | 然后他慢慢地说，但我仍然听不懂他。"
    },
    {
      "time": 66.65,
      "english": "My teacher never spoke English like that!",
      "chinese": "我的老师从来没有那样说过英语！",
      "raw": "My teacher never spoke English like that! | 我的老师从来没有那样说过英语！"
    },
    {
      "time": 71.18,
      "english": "The porter and I looked at each other and smiled.",
      "chinese": "搬运工和我互相对视，然后笑了。",
      "raw": "The porter and I looked at each other and smiled. | 搬运工和我互相对视，然后笑了。"
    },
    {
      "time": 75.41,
      "english": "Then he said something and I understood it.",
      "chinese": "然后他说了一些话，我听懂了。",
      "raw": "Then he said something and I understood it. | 然后他说了一些话，我听懂了。"
    },
    {
      "time": 79.64,
      "english": "'You'll soon learn English!' he said.",
      "chinese": "“你很快就会学好英语的！”他说。",
      "raw": "'You'll soon learn English!' he said. | “你很快就会学好英语的！”他说。"
    },
    {
      "time": 83.82,
      "english": "I wonder.",
      "chinese": "我怀疑。",
      "raw": "I wonder. | 我怀疑。"
    },
    {
      "time": 86.03,
      "english": "In England, each person speaks a different language.",
      "chinese": "在英国，每个人都说着不同的语言。",
      "raw": "In England, each person speaks a different language. | 在英国，每个人都说着不同的语言。"
    },
    {
      "time": 91.0,
      "english": "The English understand each other, but I don't understand them!",
      "chinese": "英国人彼此听得懂，但我听不懂他们！",
      "raw": "The English understand each other, but I don't understand them! | 英国人彼此听得懂，但我听不懂他们！"
    }
  ]
}